cputester/__init__.py
cputester/core.py
cputester-0.1.2.dist-info/METADATA
cputester-0.1.2.dist-info/WHEEL
cputester-0.1.2.dist-info/top_level.txt
cputester-0.1.2.dist-info/RECORD
