Metadata-Version: 2.4
Name: cputester
Version: 0.1.2
Summary: Ultimate CPU Stress Testing Library
Author-email: 2AM mimo! <fearmimo2012@gmail.com>
License: MIT
Requires-Python: >=3.9
Requires-Dist: psutil
Requires-Dist: colorama
Requires-Dist: ipython
